ezsuma.py
ezsuma-0.1.0.dist-info/METADATA
ezsuma-0.1.0.dist-info/WHEEL
ezsuma-0.1.0.dist-info/entry_points.txt
ezsuma-0.1.0.dist-info/top_level.txt
ezsuma-0.1.0.dist-info/RECORD
