Metadata-Version: 2.4
Name: ezsuma
Version: 0.1.0
Summary: Add your description here
Requires-Python: >=3.11
Requires-Dist: polars>=1.36.1
Requires-Dist: textual>=6.10.0
Requires-Dist: textual-fspicker>=0.6.0
